subnetfinder/__init__.py
subnetfinder/__main__.py
subnetfinder/subnetfinder.py
subnetfinder-1.2.1.dist-info/METADATA
subnetfinder-1.2.1.dist-info/WHEEL
subnetfinder-1.2.1.dist-info/entry_points.txt
subnetfinder-1.2.1.dist-info/top_level.txt
subnetfinder-1.2.1.dist-info/RECORD
