Metadata-Version: 2.1
Name: subnetfinder
Version: 1.2.1
Summary: Find available subnets within a given block of IPs
Home-page: https://sourceforge.net/projects/available-subnet-finder/
Author: Skylight 2000
License: MIT
Platform: UNKNOWN
Classifier: License :: OSI Approved :: MIT License
Classifier: Programming Language :: Python :: 3.7
Requires-Python: >=3.7
